{
  "w1d1": { "name": "LUNES", "title": "La Guarida del Mal" },
  "w1d2": { "name": "MARTES", "title": "Espectros del Abismo" },
  "w1d3": { "name": "MIÉRCOLES", "title": "Brujo de las Sombras" },
  "w1d4": { "name": "JUEVES", "title": "Gólem de Hierro" },
  "w1d5": { "name": "VIERNES", "title": "Gargantúa" },
  "w1d6": { "name": "SÁBADO", "title": "Hordas del Infierno" },
  "w1d7": { "name": "DOMINGO", "title": "Descanso Activo" },
  "w2d1": { "name": "LUNES", "title": "La Guarida del Mal V2" },
  "w2d2": { "name": "MARTES", "title": "Espectros V2" },
  "w2d3": { "name": "MIÉRCOLES", "title": "Brujo V2" },
  "w2d4": { "name": "JUEVES", "title": "Gólem V2" },
  "w2d5": { "name": "VIERNES", "title": "Gargantúa V2" },
  "w2d6": { "name": "SÁBADO", "title": "Hordas V2" },
  "w2d7": { "name": "DOMINGO", "title": "Tavern Portal" },
  "w3d1": { "name": "LUNES", "title": "La Guarida del Mal V3" },
  "w3d2": { "name": "MARTES", "title": "Espectros V3" },
  "w3d3": { "name": "MIÉRCOLES", "title": "Brujo V3" },
  "w3d4": { "name": "JUEVES", "title": "Gólem V3" },
  "w3d5": { "name": "VIERNES", "title": "Gargantúa V3" },
  "w3d6": { "name": "SÁBADO", "title": "ANDARIEL" },
  "w3d7": { "name": "DOMINGO", "title": "Tavern Portal" },
  "w4d1": { "name": "LUNES", "title": "La Guarida del Mal V4" },
  "w4d2": { "name": "MARTES", "title": "Espectros V4" },
  "w4d3": { "name": "MIÉRCOLES", "title": "Brujo V4" },
  "w4d4": { "name": "JUEVES", "title": "Gólem V4" },
  "w4d5": { "name": "VIERNES", "title": "Gargantúa V4" },
  "w4d6": { "name": "LUT GHOLEIN", "title": "Social Party" },
  "w4d7": { "name": "DOMINGO", "title": "Tavern Portal" }
}
